cycle_analysis/__init__.py
cycle_analysis/cycle_tools.py
cycle_analysis/cycle_tools_coalescence.py
cycle_analysis/cycle_tools_simple.py
cycle_analysis/test.py
cycle_analysis-0.0.3.dist-info/LICENSE
cycle_analysis-0.0.3.dist-info/METADATA
cycle_analysis-0.0.3.dist-info/WHEEL
cycle_analysis-0.0.3.dist-info/top_level.txt
cycle_analysis-0.0.3.dist-info/RECORD
