Metadata-Version: 2.1
Name: cycle-analysis
Version: 0.0.3
Summary: cycle_analysis module, performing minimal cycle basis calculation and cycle coalescecne.
Home-page: https://github.com/felixk1990/cycle-coalescence-algorithm
Author: felixk1990
Author-email: felixuwekramer@protonmail.com
License: UNKNOWN
Platform: UNKNOWN
Classifier: Programming Language :: Python :: 3
Classifier: License :: OSI Approved :: MIT License
Classifier: Operating System :: OS Independent
Requires-Python: >=3.6
